README
setup.cfg
setup.py
colorfulprinter/__init__.py
colorfulprinter/compat.py
colorfulprinter/npprint.py
colorfulprinter/termcolor.py
colorfulprinter.egg-info/PKG-INFO
colorfulprinter.egg-info/SOURCES.txt
colorfulprinter.egg-info/dependency_links.txt
colorfulprinter.egg-info/top_level.txt
colorfulprinter.egg-info/zip-safe
tests/__init__.py
tests/test.py