Metadata-Version: 1.1
Name: colorfulprinter
Version: 0.8.0
Summary: A drop in replacement for python built-in pprint package
Home-page: https://github.com/drinksober/colorfulprinter
Author: drink
Author-email: drinksober@foxmail.com
License: MIT
Keywords: python pprint color console terminal unicode
Platform: UNKNOWN
Classifier: Development Status :: 3 - Alpha
Classifier: Intended Audience :: Developers
Classifier: Topic :: Software Development
Classifier: License :: OSI Approved :: MIT License
Classifier: Programming Language :: Python :: 2.7
Classifier: Programming Language :: Python :: 3.5
